Metadata-Version: 2.4
Name: az-perfwatch
Version: 1.0.2
Summary: Production-ready performance monitoring library for Python web applications
Home-page: https://github.com/ShahabazAlam/az-perfwatch
Author: Shahabaz Alam
Author-email: Shahabaz Alam <shahabazalam1@gmail.com>
License-Expression: MIT
Project-URL: Homepage, https://github.com/ShahabazAlam/az-perfwatch
Project-URL: Repository, https://github.com/ShahabazAlam/az-perfwatch
Project-URL: Bug Reports, https://github.com/ShahabazAlam/az-perfwatch/issues
Project-URL: Documentation, https://github.com/ShahabazAlam/az-perfwatch#readme
Keywords: performance,monitoring,profiling,django,flask,fastapi,metrics
Classifier: Development Status :: 4 - Beta
Classifier: Intended Audience :: Developers
Classifier: Topic :: Software Development :: Libraries :: Python Modules
Classifier: Topic :: System :: Monitoring
Classifier: Programming Language :: Python :: 3
Classifier: Programming Language :: Python :: 3.8
Classifier: Programming Language :: Python :: 3.9
Classifier: Programming Language :: Python :: 3.10
Classifier: Programming Language :: Python :: 3.11
Classifier: Programming Language :: Python :: 3.12
Classifier: Framework :: Django
Classifier: Framework :: Flask
Classifier: Framework :: FastAPI
Classifier: Operating System :: OS Independent
Requires-Python: >=3.8
License-File: LICENSE
Requires-Dist: fastapi>=0.100.0
Requires-Dist: flask>=2.3.2
Requires-Dist: django>=4.2
Requires-Dist: sqlalchemy>=2.0
Requires-Dist: pymongo>=4.10.0
Requires-Dist: requests>=2.31.0
Requires-Dist: httpx>=0.24.0
Requires-Dist: pydantic>=2.5.0
Requires-Dist: rich>=13.4
Requires-Dist: jinja2>=3.1
Requires-Dist: uvicorn>=0.25.0
Requires-Dist: toml>=0.10
Requires-Dist: passlib[bcrypt]>=1.7.4
Requires-Dist: typer>=0.9.0
Requires-Dist: psycopg2-binary>=2.9.0
Requires-Dist: mysql-connector-python>=8.0.0
Provides-Extra: dev
Requires-Dist: pytest>=7.0.0; extra == "dev"
Requires-Dist: pytest-cov>=4.0.0; extra == "dev"
Requires-Dist: black>=24.0.0; extra == "dev"
Requires-Dist: isort>=5.12.0; extra == "dev"
Requires-Dist: flake8>=6.0.0; extra == "dev"
Requires-Dist: mypy>=1.10.0; extra == "dev"
Dynamic: author
Dynamic: home-page
Dynamic: license-file
Dynamic: requires-python
